Metadata-Version: 2.1
Name: straw-codec
Version: 0.4
Summary: Lossless codec for multichannel audio
Home-page: https://github.com/KLZ-0/straw/
Author: KLZ-0
Author-email: adrian@kalazi.com
License: UNKNOWN
Platform: UNKNOWN
Classifier: Programming Language :: Python :: 3
Classifier: License :: OSI Approved :: MIT License
Classifier: Operating System :: OS Independent
Requires-Python: >=3.6
License-File: LICENSE
